play_takeout_to_plex/__init__.py
play_takeout_to_plex/songs.py
play_takeout_to_plex/takeout_converter.py
play_takeout_to_plex-0.1.3.dist-info/entry_points.txt
play_takeout_to_plex-0.1.3.dist-info/LICENSE
play_takeout_to_plex-0.1.3.dist-info/WHEEL
play_takeout_to_plex-0.1.3.dist-info/METADATA
play_takeout_to_plex-0.1.3.dist-info/RECORD
